qiboml/__init__.py
qiboml/backends/__init__.py
qiboml/backends/jax.py
qiboml/backends/pytorch.py
qiboml/backends/tensorflow.py
qiboml/interfaces/circuit_tracer.py
qiboml/interfaces/keras.py
qiboml/interfaces/pytorch.py
qiboml/interfaces/utils.py
qiboml/models/ansatze.py
qiboml/models/calibrator.py
qiboml/models/decoding.py
qiboml/models/encoding.py
qiboml/models/optimizers.py
qiboml/models/utils.py
qiboml/operations/differentiation.py
qiboml-0.1.0.dist-info/METADATA
qiboml-0.1.0.dist-info/WHEEL
qiboml-0.1.0.dist-info/licenses/LICENSE
qiboml-0.1.0.dist-info/RECORD
