Metadata-Version: 2.4
Name: qiboml
Version: 0.1.0
Summary: Quantum Machine Learning using Qibo
License-File: LICENSE
Author: Qiboteam
Requires-Python: >=3.10,<3.14
Classifier: Programming Language :: Python :: 3
Classifier: Programming Language :: Python :: 3.10
Classifier: Programming Language :: Python :: 3.11
Classifier: Programming Language :: Python :: 3.12
Classifier: Programming Language :: Python :: 3.13
Provides-Extra: keras
Provides-Extra: torch
Requires-Dist: jax (>=0.4.25,<0.5.0)
Requires-Dist: jaxlib (>=0.4.25,<0.5.0)
Requires-Dist: keras (>=3.11.0,<4.0.0) ; extra == "keras"
Requires-Dist: numpy (>=2.0.0,<3.0.0)
Requires-Dist: qibo (>=0.2.21,<0.3.0)
Requires-Dist: tensorflow (>=2.16.1,<3.0.0) ; (sys_platform == "linux" or sys_platform == "darwin") and (extra == "keras")
Requires-Dist: torch (>=2.7.0,<3.0.0) ; extra == "torch"
Project-URL: Documentation, https://qibo.science/docs/qiboml/stable
Project-URL: Homepage, https://qibo.science/
Project-URL: Repository, https://github.com/qiboteam/qiboml/
